[
  {
    "type": "seeed_gfx_setup",
    "message0": "初始化 Seeed_GFX %1 型号 %2 SPI频率 %3 宽 %4 高 %5 MISO %6 MOSI %7 SCLK %8 CS %9 DC %10 RST %11 BL %12 背光 %13 颜色顺序 %14 旋转 %15",
    "args0": [
      { "type": "field_input", "name": "VAR", "text": "tft" },
      { "type": "field_dropdown", "name": "MODEL", "options": [["ST7789", "ST7789_DRIVER"], ["ILI9341", "ILI9341_DRIVER"], ["ILI9488", "ILI9488_DRIVER"], ["GC9A01", "GC9A01_DRIVER"], ["GC9D01", "GC9D01_DRIVER"], ["ST7735", "ST7735_DRIVER"], ["ILI9163", "ILI9163_DRIVER"], ["RM68140", "RM68140_DRIVER"], ["ST7796", "ST7796_DRIVER"], ["SSD1351", "SSD1351_DRIVER"]] },
      { "type": "field_dropdown", "name": "FREQUENCY", "options": [["10MHz", "10000000"], ["20MHz", "20000000"], ["27MHz", "27000000"], ["40MHz", "40000000"], ["55MHz", "55000000"], ["80MHz", "80000000"]] },
      { "type": "input_value", "name": "WIDTH", "check": ["Number"] },
      { "type": "input_value", "name": "HEIGHT", "check": ["Number"] },
      { "type": "input_value", "name": "MISO", "check": ["Number"] },
      { "type": "input_value", "name": "MOSI", "check": ["Number"] },
      { "type": "input_value", "name": "SCLK", "check": ["Number"] },
      { "type": "input_value", "name": "CS", "check": ["Number"] },
      { "type": "input_value", "name": "DC", "check": ["Number"] },
      { "type": "input_value", "name": "RST", "check": ["Number"] },
      { "type": "input_value", "name": "BL", "check": ["Number"] },
      { "type": "field_dropdown", "name": "BL_LEVEL", "options": [["高电平点亮", "HIGH"], ["低电平点亮", "LOW"]] },
      { "type": "field_dropdown", "name": "COLOR_MODE", "options": [["RGB", "TFT_RGB"], ["BGR", "TFT_BGR"]] },
      { "type": "field_dropdown", "name": "ROTATION", "options": [["0度", "0"], ["90度", "1"], ["180度", "2"], ["270度", "3"]] }
    ],
    "inputsInline": false,
    "previousStatement": null,
    "nextStatement": null,
    "colour": "#009688",
    "tooltip": "配置并初始化 Seeed_GFX/TFT_eSPI 显示对象",
    "icon": "fa-light fa-display"
  },
  {
    "type": "seeed_gfx_set_rotation",
    "message0": "Seeed_GFX %1 设置旋转 %2",
    "args0": [
      { "type": "field_variable", "name": "VAR", "variable": "tft", "variableTypes": ["TFT_eSPI"], "defaultType": "TFT_eSPI" },
      { "type": "field_dropdown", "name": "ROTATION", "options": [["0度", "0"], ["90度", "1"], ["180度", "2"], ["270度", "3"]] }
    ],
    "previousStatement": null,
    "nextStatement": null,
    "colour": "#009688",
    "tooltip": "设置屏幕方向",
    "icon": "fa-light fa-rotate-right"
  },
  {
    "type": "seeed_gfx_invert_display",
    "message0": "Seeed_GFX %1 反色显示 %2",
    "args0": [
      { "type": "field_variable", "name": "VAR", "variable": "tft", "variableTypes": ["TFT_eSPI"], "defaultType": "TFT_eSPI" },
      { "type": "field_dropdown", "name": "INVERT", "options": [["开启", "true"], ["关闭", "false"]] }
    ],
    "previousStatement": null,
    "nextStatement": null,
    "colour": "#009688",
    "tooltip": "开启或关闭屏幕反色",
    "icon": "fa-light fa-circle-half-stroke"
  },
  {
    "type": "seeed_gfx_fill_screen",
    "message0": "Seeed_GFX %1 填充屏幕 颜色 %2",
    "args0": [
      { "type": "field_variable", "name": "VAR", "variable": "tft", "variableTypes": ["TFT_eSPI"], "defaultType": "TFT_eSPI" },
      { "type": "input_value", "name": "COLOR" }
    ],
    "previousStatement": null,
    "nextStatement": null,
    "colour": "#00BCD4",
    "tooltip": "用指定颜色清屏",
    "icon": "fa-light fa-fill-drip"
  },
  {
    "type": "seeed_gfx_draw_pixel",
    "message0": "Seeed_GFX %1 画点 X %2 Y %3 颜色 %4",
    "args0": [
      { "type": "field_variable", "name": "VAR", "variable": "tft", "variableTypes": ["TFT_eSPI"], "defaultType": "TFT_eSPI" },
      { "type": "input_value", "name": "X", "check": ["Number"] },
      { "type": "input_value", "name": "Y", "check": ["Number"] },
      { "type": "input_value", "name": "COLOR" }
    ],
    "inputsInline": true,
    "previousStatement": null,
    "nextStatement": null,
    "colour": "#00BCD4",
    "tooltip": "绘制一个像素点",
    "icon": "fa-light fa-pen-nib"
  },
  {
    "type": "seeed_gfx_draw_line",
    "message0": "Seeed_GFX %1 画线 X1 %2 Y1 %3 X2 %4 Y2 %5 颜色 %6",
    "args0": [
      { "type": "field_variable", "name": "VAR", "variable": "tft", "variableTypes": ["TFT_eSPI"], "defaultType": "TFT_eSPI" },
      { "type": "input_value", "name": "X1", "check": ["Number"] },
      { "type": "input_value", "name": "Y1", "check": ["Number"] },
      { "type": "input_value", "name": "X2", "check": ["Number"] },
      { "type": "input_value", "name": "Y2", "check": ["Number"] },
      { "type": "input_value", "name": "COLOR" }
    ],
    "inputsInline": true,
    "previousStatement": null,
    "nextStatement": null,
    "colour": "#00BCD4",
    "tooltip": "绘制线段",
    "icon": "fa-light fa-slash"
  },
  {
    "type": "seeed_gfx_draw_rect",
    "message0": "Seeed_GFX %1 画矩形 X %2 Y %3 宽 %4 高 %5 颜色 %6",
    "args0": [
      { "type": "field_variable", "name": "VAR", "variable": "tft", "variableTypes": ["TFT_eSPI"], "defaultType": "TFT_eSPI" },
      { "type": "input_value", "name": "X", "check": ["Number"] },
      { "type": "input_value", "name": "Y", "check": ["Number"] },
      { "type": "input_value", "name": "W", "check": ["Number"] },
      { "type": "input_value", "name": "H", "check": ["Number"] },
      { "type": "input_value", "name": "COLOR" }
    ],
    "inputsInline": true,
    "previousStatement": null,
    "nextStatement": null,
    "colour": "#00BCD4",
    "tooltip": "绘制矩形边框",
    "icon": "fa-light fa-square"
  },
  {
    "type": "seeed_gfx_fill_rect",
    "message0": "Seeed_GFX %1 填充矩形 X %2 Y %3 宽 %4 高 %5 颜色 %6",
    "args0": [
      { "type": "field_variable", "name": "VAR", "variable": "tft", "variableTypes": ["TFT_eSPI"], "defaultType": "TFT_eSPI" },
      { "type": "input_value", "name": "X", "check": ["Number"] },
      { "type": "input_value", "name": "Y", "check": ["Number"] },
      { "type": "input_value", "name": "W", "check": ["Number"] },
      { "type": "input_value", "name": "H", "check": ["Number"] },
      { "type": "input_value", "name": "COLOR" }
    ],
    "inputsInline": true,
    "previousStatement": null,
    "nextStatement": null,
    "colour": "#00BCD4",
    "tooltip": "绘制填充矩形",
    "icon": "fa-light fa-square-full"
  },
  {
    "type": "seeed_gfx_draw_circle",
    "message0": "Seeed_GFX %1 画圆 X %2 Y %3 半径 %4 颜色 %5",
    "args0": [
      { "type": "field_variable", "name": "VAR", "variable": "tft", "variableTypes": ["TFT_eSPI"], "defaultType": "TFT_eSPI" },
      { "type": "input_value", "name": "X", "check": ["Number"] },
      { "type": "input_value", "name": "Y", "check": ["Number"] },
      { "type": "input_value", "name": "RADIUS", "check": ["Number"] },
      { "type": "input_value", "name": "COLOR" }
    ],
    "inputsInline": true,
    "previousStatement": null,
    "nextStatement": null,
    "colour": "#00BCD4",
    "tooltip": "绘制圆形边框",
    "icon": "fa-light fa-circle"
  },
  {
    "type": "seeed_gfx_fill_circle",
    "message0": "Seeed_GFX %1 填充圆 X %2 Y %3 半径 %4 颜色 %5",
    "args0": [
      { "type": "field_variable", "name": "VAR", "variable": "tft", "variableTypes": ["TFT_eSPI"], "defaultType": "TFT_eSPI" },
      { "type": "input_value", "name": "X", "check": ["Number"] },
      { "type": "input_value", "name": "Y", "check": ["Number"] },
      { "type": "input_value", "name": "RADIUS", "check": ["Number"] },
      { "type": "input_value", "name": "COLOR" }
    ],
    "inputsInline": true,
    "previousStatement": null,
    "nextStatement": null,
    "colour": "#00BCD4",
    "tooltip": "绘制填充圆",
    "icon": "fa-light fa-circle-dot"
  },
  {
    "type": "seeed_gfx_draw_triangle",
    "message0": "Seeed_GFX %1 画三角形 X1 %2 Y1 %3 X2 %4 Y2 %5 X3 %6 Y3 %7 颜色 %8",
    "args0": [
      { "type": "field_variable", "name": "VAR", "variable": "tft", "variableTypes": ["TFT_eSPI"], "defaultType": "TFT_eSPI" },
      { "type": "input_value", "name": "X1", "check": ["Number"] },
      { "type": "input_value", "name": "Y1", "check": ["Number"] },
      { "type": "input_value", "name": "X2", "check": ["Number"] },
      { "type": "input_value", "name": "Y2", "check": ["Number"] },
      { "type": "input_value", "name": "X3", "check": ["Number"] },
      { "type": "input_value", "name": "Y3", "check": ["Number"] },
      { "type": "input_value", "name": "COLOR" }
    ],
    "inputsInline": true,
    "previousStatement": null,
    "nextStatement": null,
    "colour": "#00BCD4",
    "tooltip": "绘制三角形边框",
    "icon": "fa-light fa-play"
  },
  {
    "type": "seeed_gfx_fill_triangle",
    "message0": "Seeed_GFX %1 填充三角形 X1 %2 Y1 %3 X2 %4 Y2 %5 X3 %6 Y3 %7 颜色 %8",
    "args0": [
      { "type": "field_variable", "name": "VAR", "variable": "tft", "variableTypes": ["TFT_eSPI"], "defaultType": "TFT_eSPI" },
      { "type": "input_value", "name": "X1", "check": ["Number"] },
      { "type": "input_value", "name": "Y1", "check": ["Number"] },
      { "type": "input_value", "name": "X2", "check": ["Number"] },
      { "type": "input_value", "name": "Y2", "check": ["Number"] },
      { "type": "input_value", "name": "X3", "check": ["Number"] },
      { "type": "input_value", "name": "Y3", "check": ["Number"] },
      { "type": "input_value", "name": "COLOR" }
    ],
    "inputsInline": true,
    "previousStatement": null,
    "nextStatement": null,
    "colour": "#00BCD4",
    "tooltip": "绘制填充三角形",
    "icon": "fa-light fa-play"
  },
  {
    "type": "seeed_gfx_draw_round_rect",
    "message0": "Seeed_GFX %1 画圆角矩形 X %2 Y %3 宽 %4 高 %5 半径 %6 颜色 %7",
    "args0": [
      { "type": "field_variable", "name": "VAR", "variable": "tft", "variableTypes": ["TFT_eSPI"], "defaultType": "TFT_eSPI" },
      { "type": "input_value", "name": "X", "check": ["Number"] },
      { "type": "input_value", "name": "Y", "check": ["Number"] },
      { "type": "input_value", "name": "W", "check": ["Number"] },
      { "type": "input_value", "name": "H", "check": ["Number"] },
      { "type": "input_value", "name": "RADIUS", "check": ["Number"] },
      { "type": "input_value", "name": "COLOR" }
    ],
    "inputsInline": true,
    "previousStatement": null,
    "nextStatement": null,
    "colour": "#00BCD4",
    "tooltip": "绘制圆角矩形边框",
    "icon": "fa-light fa-vector-square"
  },
  {
    "type": "seeed_gfx_fill_round_rect",
    "message0": "Seeed_GFX %1 填充圆角矩形 X %2 Y %3 宽 %4 高 %5 半径 %6 颜色 %7",
    "args0": [
      { "type": "field_variable", "name": "VAR", "variable": "tft", "variableTypes": ["TFT_eSPI"], "defaultType": "TFT_eSPI" },
      { "type": "input_value", "name": "X", "check": ["Number"] },
      { "type": "input_value", "name": "Y", "check": ["Number"] },
      { "type": "input_value", "name": "W", "check": ["Number"] },
      { "type": "input_value", "name": "H", "check": ["Number"] },
      { "type": "input_value", "name": "RADIUS", "check": ["Number"] },
      { "type": "input_value", "name": "COLOR" }
    ],
    "inputsInline": true,
    "previousStatement": null,
    "nextStatement": null,
    "colour": "#00BCD4",
    "tooltip": "绘制填充圆角矩形",
    "icon": "fa-light fa-vector-square"
  },
  {
    "type": "seeed_gfx_set_text_style",
    "message0": "Seeed_GFX %1 文字样式 字色 %2 背景 %3 大小 %4 字体 %5",
    "args0": [
      { "type": "field_variable", "name": "VAR", "variable": "tft", "variableTypes": ["TFT_eSPI"], "defaultType": "TFT_eSPI" },
      { "type": "input_value", "name": "TEXT_COLOR" },
      { "type": "input_value", "name": "BG_COLOR" },
      { "type": "field_dropdown", "name": "SIZE", "options": [["1", "1"], ["2", "2"], ["3", "3"], ["4", "4"], ["5", "5"], ["6", "6"], ["7", "7"]] },
      { "type": "field_dropdown", "name": "FONT", "options": [["GLCD", "1"], ["Font2", "2"], ["Font4", "4"], ["Font6", "6"], ["Font7", "7"], ["Font8", "8"]] }
    ],
    "previousStatement": null,
    "nextStatement": null,
    "colour": "#3F51B5",
    "tooltip": "设置 TFT 文字颜色、大小和字体",
    "icon": "fa-light fa-font"
  },
  {
    "type": "seeed_gfx_draw_string",
    "message0": "Seeed_GFX %1 在 X %2 Y %3 显示文本 %4",
    "args0": [
      { "type": "field_variable", "name": "VAR", "variable": "tft", "variableTypes": ["TFT_eSPI"], "defaultType": "TFT_eSPI" },
      { "type": "input_value", "name": "X", "check": ["Number"] },
      { "type": "input_value", "name": "Y", "check": ["Number"] },
      { "type": "input_value", "name": "TEXT", "check": ["String"] }
    ],
    "previousStatement": null,
    "nextStatement": null,
    "colour": "#3F51B5",
    "tooltip": "在指定坐标绘制字符串",
    "icon": "fa-light fa-font"
  },
  {
    "type": "seeed_gfx_set_cursor",
    "message0": "Seeed_GFX %1 设置光标 X %2 Y %3",
    "args0": [
      { "type": "field_variable", "name": "VAR", "variable": "tft", "variableTypes": ["TFT_eSPI"], "defaultType": "TFT_eSPI" },
      { "type": "input_value", "name": "X", "check": ["Number"] },
      { "type": "input_value", "name": "Y", "check": ["Number"] }
    ],
    "previousStatement": null,
    "nextStatement": null,
    "colour": "#3F51B5",
    "tooltip": "设置 print/println 光标位置",
    "icon": "fa-light fa-i-cursor"
  },
  {
    "type": "seeed_gfx_print",
    "message0": "Seeed_GFX %1 打印 %2 换行 %3",
    "args0": [
      { "type": "field_variable", "name": "VAR", "variable": "tft", "variableTypes": ["TFT_eSPI"], "defaultType": "TFT_eSPI" },
      { "type": "input_value", "name": "TEXT" },
      { "type": "field_dropdown", "name": "NEWLINE", "options": [["是", "true"], ["否", "false"]] }
    ],
    "previousStatement": null,
    "nextStatement": null,
    "colour": "#3F51B5",
    "tooltip": "使用 Print 接口输出文本或数值",
    "icon": "fa-light fa-print"
  },
  {
    "type": "seeed_gfx_color",
    "message0": "TFT 颜色 %1",
    "args0": [
      { "type": "field_dropdown", "name": "COLOR", "options": [["黑色", "TFT_BLACK"], ["白色", "TFT_WHITE"], ["红色", "TFT_RED"], ["绿色", "TFT_GREEN"], ["蓝色", "TFT_BLUE"], ["黄色", "TFT_YELLOW"], ["青色", "TFT_CYAN"], ["洋红", "TFT_MAGENTA"], ["橙色", "TFT_ORANGE"], ["浅灰", "TFT_LIGHTGREY"], ["深灰", "TFT_DARKGREY"]] }
    ],
    "output": "Number",
    "colour": "#3F51B5",
    "tooltip": "TFT_eSPI 预设 RGB565 颜色",
    "icon": "fa-light fa-palette"
  },
  {
    "type": "seeed_gfx_color_rgb",
    "message0": "TFT RGB565 颜色 %1",
    "args0": [{ "type": "field_colour_hsv_sliders", "name": "COLOR", "colour": "#ffffff" }],
    "output": "Number",
    "colour": "#3F51B5",
    "tooltip": "将颜色选择器转换为 RGB565 常量",
    "icon": "fa-light fa-eye-dropper"
  },
  {
    "type": "seeed_gfx_width",
    "message0": "Seeed_GFX %1 宽度",
    "args0": [{ "type": "field_variable", "name": "VAR", "variable": "tft", "variableTypes": ["TFT_eSPI"], "defaultType": "TFT_eSPI" }],
    "output": "Number",
    "colour": "#009688",
    "tooltip": "获取当前屏幕宽度",
    "icon": "fa-light fa-ruler-horizontal"
  },
  {
    "type": "seeed_gfx_height",
    "message0": "Seeed_GFX %1 高度",
    "args0": [{ "type": "field_variable", "name": "VAR", "variable": "tft", "variableTypes": ["TFT_eSPI"], "defaultType": "TFT_eSPI" }],
    "output": "Number",
    "colour": "#009688",
    "tooltip": "获取当前屏幕高度",
    "icon": "fa-light fa-ruler-vertical"
  },
  {
    "type": "seeed_gfx_read_touch",
    "message0": "Seeed_GFX %1 读取触摸 X变量 %2 Y变量 %3 状态变量 %4 阈值 %5",
    "args0": [
      { "type": "field_variable", "name": "VAR", "variable": "tft", "variableTypes": ["TFT_eSPI"], "defaultType": "TFT_eSPI" },
      { "type": "field_input", "name": "XVAR", "text": "touchX" },
      { "type": "field_input", "name": "YVAR", "text": "touchY" },
      { "type": "field_input", "name": "TOUCHVAR", "text": "touched" },
      { "type": "input_value", "name": "THRESHOLD", "check": ["Number"] }
    ],
    "previousStatement": null,
    "nextStatement": null,
    "colour": "#795548",
    "tooltip": "读取触摸屏坐标并写入变量",
    "icon": "fa-light fa-hand-pointer"
  },
  {
    "type": "seeed_gfx_touch_pressed",
    "message0": "Seeed_GFX %1 是否触摸 阈值 %2",
    "args0": [
      { "type": "field_variable", "name": "VAR", "variable": "tft", "variableTypes": ["TFT_eSPI"], "defaultType": "TFT_eSPI" },
      { "type": "input_value", "name": "THRESHOLD", "check": ["Number"] }
    ],
    "output": "Boolean",
    "colour": "#795548",
    "tooltip": "返回触摸屏是否被按下",
    "icon": "fa-light fa-hand-pointer"
  },
  {
    "type": "seeed_gfx_sprite_create",
    "message0": "创建 Sprite %1 绑定屏幕 %2 宽 %3 高 %4 色深 %5",
    "args0": [
      { "type": "field_input", "name": "VAR", "text": "sprite" },
      { "type": "field_variable", "name": "TFT", "variable": "tft", "variableTypes": ["TFT_eSPI"], "defaultType": "TFT_eSPI" },
      { "type": "input_value", "name": "WIDTH", "check": ["Number"] },
      { "type": "input_value", "name": "HEIGHT", "check": ["Number"] },
      { "type": "field_dropdown", "name": "DEPTH", "options": [["1 bit", "1"], ["4 bit", "4"], ["8 bit", "8"], ["16 bit", "16"]] }
    ],
    "previousStatement": null,
    "nextStatement": null,
    "colour": "#607D8B",
    "tooltip": "创建离屏 Sprite 缓冲区",
    "icon": "fa-light fa-layer-group"
  },
  {
    "type": "seeed_gfx_sprite_set_depth",
    "message0": "Sprite %1 设置色深 %2",
    "args0": [
      { "type": "field_variable", "name": "VAR", "variable": "sprite", "variableTypes": ["TFT_eSprite"], "defaultType": "TFT_eSprite" },
      { "type": "field_dropdown", "name": "DEPTH", "options": [["1 bit", "1"], ["4 bit", "4"], ["8 bit", "8"], ["16 bit", "16"]] }
    ],
    "previousStatement": null,
    "nextStatement": null,
    "colour": "#607D8B",
    "tooltip": "设置 Sprite 色深",
    "icon": "fa-light fa-layer-group"
  },
  {
    "type": "seeed_gfx_sprite_fill",
    "message0": "Sprite %1 填充颜色 %2",
    "args0": [
      { "type": "field_variable", "name": "VAR", "variable": "sprite", "variableTypes": ["TFT_eSprite"], "defaultType": "TFT_eSprite" },
      { "type": "input_value", "name": "COLOR" }
    ],
    "previousStatement": null,
    "nextStatement": null,
    "colour": "#607D8B",
    "tooltip": "填充 Sprite 背景",
    "icon": "fa-light fa-fill"
  },
  {
    "type": "seeed_gfx_sprite_push",
    "message0": "Sprite %1 推送到屏幕 X %2 Y %3",
    "args0": [
      { "type": "field_variable", "name": "VAR", "variable": "sprite", "variableTypes": ["TFT_eSprite"], "defaultType": "TFT_eSprite" },
      { "type": "input_value", "name": "X", "check": ["Number"] },
      { "type": "input_value", "name": "Y", "check": ["Number"] }
    ],
    "previousStatement": null,
    "nextStatement": null,
    "colour": "#607D8B",
    "tooltip": "把 Sprite 绘制到 TFT 屏幕",
    "icon": "fa-light fa-share-from-square"
  },
  {
    "type": "seeed_gfx_sprite_delete",
    "message0": "删除 Sprite %1",
    "args0": [{ "type": "field_variable", "name": "VAR", "variable": "sprite", "variableTypes": ["TFT_eSprite"], "defaultType": "TFT_eSprite" }],
    "previousStatement": null,
    "nextStatement": null,
    "colour": "#607D8B",
    "tooltip": "释放 Sprite 内存",
    "icon": "fa-light fa-trash"
  },
  {
    "type": "seeed_gfx_epaper_setup",
    "message0": "初始化 E-Paper %1 唤醒模式 %2",
    "args0": [
      { "type": "field_input", "name": "VAR", "text": "epaper" },
      { "type": "field_dropdown", "name": "WAKE", "options": [["默认", "0"], ["唤醒", "1"]] }
    ],
    "previousStatement": null,
    "nextStatement": null,
    "colour": "#455A64",
    "tooltip": "启用 EPAPER_ENABLE 并初始化 EPaper 对象",
    "icon": "fa-light fa-note-sticky"
  },
  {
    "type": "seeed_gfx_epaper_update",
    "message0": "E-Paper %1 全屏刷新",
    "args0": [{ "type": "field_variable", "name": "VAR", "variable": "epaper", "variableTypes": ["EPaper"], "defaultType": "EPaper" }],
    "previousStatement": null,
    "nextStatement": null,
    "colour": "#455A64",
    "tooltip": "刷新 E-Paper 显示",
    "icon": "fa-light fa-arrows-rotate"
  },
  {
    "type": "seeed_gfx_epaper_sleep",
    "message0": "E-Paper %1 休眠",
    "args0": [{ "type": "field_variable", "name": "VAR", "variable": "epaper", "variableTypes": ["EPaper"], "defaultType": "EPaper" }],
    "previousStatement": null,
    "nextStatement": null,
    "colour": "#455A64",
    "tooltip": "让 E-Paper 进入休眠",
    "icon": "fa-light fa-moon"
  },
  {
    "type": "seeed_gfx_epaper_wake",
    "message0": "E-Paper %1 唤醒",
    "args0": [{ "type": "field_variable", "name": "VAR", "variable": "epaper", "variableTypes": ["EPaper"], "defaultType": "EPaper" }],
    "previousStatement": null,
    "nextStatement": null,
    "colour": "#455A64",
    "tooltip": "唤醒 E-Paper",
    "icon": "fa-light fa-sun"
  },
  {
    "type": "seeed_gfx_epaper_partial_update",
    "message0": "E-Paper %1 局部刷新 X %2 Y %3 宽 %4 高 %5",
    "args0": [
      { "type": "field_variable", "name": "VAR", "variable": "epaper", "variableTypes": ["EPaper"], "defaultType": "EPaper" },
      { "type": "input_value", "name": "X", "check": ["Number"] },
      { "type": "input_value", "name": "Y", "check": ["Number"] },
      { "type": "input_value", "name": "W", "check": ["Number"] },
      { "type": "input_value", "name": "H", "check": ["Number"] }
    ],
    "previousStatement": null,
    "nextStatement": null,
    "colour": "#455A64",
    "tooltip": "刷新指定 E-Paper 区域",
    "icon": "fa-light fa-crop-simple"
  },
  {
    "type": "seeed_lvgl_init",
    "message0": "初始化 Seeed LVGL 使用屏幕 %1 宽 %2 高 %3 旋转 %4 缓冲行数 %5 刷新间隔ms %6",
    "args0": [
      { "type": "field_variable", "name": "TFT", "variable": "tft", "variableTypes": ["TFT_eSPI"], "defaultType": "TFT_eSPI" },
      { "type": "input_value", "name": "WIDTH", "check": ["Number"] },
      { "type": "input_value", "name": "HEIGHT", "check": ["Number"] },
      { "type": "field_dropdown", "name": "ROTATION", "options": [["0度", "0"], ["90度", "1"], ["180度", "2"], ["270度", "3"]] },
      { "type": "input_value", "name": "BUFFER_LINES", "check": ["Number"] },
      { "type": "input_value", "name": "TICK_MS", "check": ["Number"] }
    ],
    "inputsInline": false,
    "previousStatement": null,
    "nextStatement": null,
    "colour": "#4CAF50",
    "tooltip": "按 LVGL 7 方式注册 TFT flush 驱动并自动在 loop 中处理任务",
    "icon": "fa-light fa-gauge-high"
  },
  {
    "type": "seeed_lvgl_touch_input_create",
    "message0": "创建 LVGL 触摸输入 %1 使用屏幕 %2 阈值 %3",
    "args0": [
      { "type": "field_input", "name": "VAR", "text": "indev" },
      { "type": "field_variable", "name": "TFT", "variable": "tft", "variableTypes": ["TFT_eSPI"], "defaultType": "TFT_eSPI" },
      { "type": "input_value", "name": "THRESHOLD", "check": ["Number"] }
    ],
    "previousStatement": null,
    "nextStatement": null,
    "colour": "#4CAF50",
    "tooltip": "把 Seeed_GFX 触摸读数注册为 LVGL 指针输入设备",
    "icon": "fa-light fa-hand-pointer"
  },
  {
    "type": "seeed_lvgl_screen_create",
    "message0": "创建 LVGL 屏幕 %1",
    "args0": [{ "type": "field_input", "name": "VAR", "text": "screen" }],
    "previousStatement": null,
    "nextStatement": null,
    "colour": "#8BC34A",
    "tooltip": "创建一个 LVGL 屏幕对象",
    "icon": "fa-light fa-desktop"
  },
  {
    "type": "seeed_lvgl_screen_load",
    "message0": "加载 LVGL 屏幕 %1",
    "args0": [{ "type": "field_variable", "name": "VAR", "variable": "screen", "variableTypes": ["lv_obj_t"], "defaultType": "lv_obj_t" }],
    "previousStatement": null,
    "nextStatement": null,
    "colour": "#8BC34A",
    "tooltip": "切换到指定屏幕",
    "icon": "fa-light fa-desktop"
  },
  {
    "type": "seeed_lvgl_active_screen",
    "message0": "当前 LVGL 屏幕",
    "output": "lv_obj_t",
    "colour": "#8BC34A",
    "tooltip": "返回 lv_scr_act()",
    "icon": "fa-light fa-desktop"
  },
  {
    "type": "seeed_lvgl_obj_set_pos",
    "message0": "LVGL 对象 %1 设置位置 X %2 Y %3",
    "args0": [
      { "type": "field_variable", "name": "VAR", "variable": "obj", "variableTypes": ["lv_obj_t"], "defaultType": "lv_obj_t" },
      { "type": "input_value", "name": "X", "check": ["Number"] },
      { "type": "input_value", "name": "Y", "check": ["Number"] }
    ],
    "previousStatement": null,
    "nextStatement": null,
    "colour": "#8BC34A",
    "tooltip": "设置 LVGL 对象坐标",
    "icon": "fa-light fa-arrows-up-down-left-right"
  },
  {
    "type": "seeed_lvgl_obj_set_size",
    "message0": "LVGL 对象 %1 设置尺寸 宽 %2 高 %3",
    "args0": [
      { "type": "field_variable", "name": "VAR", "variable": "obj", "variableTypes": ["lv_obj_t"], "defaultType": "lv_obj_t" },
      { "type": "input_value", "name": "W", "check": ["Number"] },
      { "type": "input_value", "name": "H", "check": ["Number"] }
    ],
    "previousStatement": null,
    "nextStatement": null,
    "colour": "#8BC34A",
    "tooltip": "设置 LVGL 对象大小",
    "icon": "fa-light fa-up-right-and-down-left-from-center"
  },
  {
    "type": "seeed_lvgl_obj_align",
    "message0": "LVGL 对象 %1 对齐 %2 偏移 X %3 Y %4",
    "args0": [
      { "type": "field_variable", "name": "VAR", "variable": "obj", "variableTypes": ["lv_obj_t"], "defaultType": "lv_obj_t" },
      { "type": "field_dropdown", "name": "ALIGN", "options": [["居中", "LV_ALIGN_CENTER"], ["顶部中间", "LV_ALIGN_IN_TOP_MID"], ["底部中间", "LV_ALIGN_IN_BOTTOM_MID"], ["左侧中间", "LV_ALIGN_IN_LEFT_MID"], ["右侧中间", "LV_ALIGN_IN_RIGHT_MID"], ["左上", "LV_ALIGN_IN_TOP_LEFT"], ["右上", "LV_ALIGN_IN_TOP_RIGHT"], ["左下", "LV_ALIGN_IN_BOTTOM_LEFT"], ["右下", "LV_ALIGN_IN_BOTTOM_RIGHT"]] },
      { "type": "input_value", "name": "X", "check": ["Number"] },
      { "type": "input_value", "name": "Y", "check": ["Number"] }
    ],
    "previousStatement": null,
    "nextStatement": null,
    "colour": "#8BC34A",
    "tooltip": "按父对象对齐 LVGL 对象",
    "icon": "fa-light fa-align-center"
  },
  {
    "type": "seeed_lvgl_obj_set_hidden",
    "message0": "LVGL 对象 %1 隐藏 %2",
    "args0": [
      { "type": "field_variable", "name": "VAR", "variable": "obj", "variableTypes": ["lv_obj_t"], "defaultType": "lv_obj_t" },
      { "type": "field_dropdown", "name": "HIDDEN", "options": [["是", "true"], ["否", "false"]] }
    ],
    "previousStatement": null,
    "nextStatement": null,
    "colour": "#8BC34A",
    "tooltip": "显示或隐藏对象",
    "icon": "fa-light fa-eye-slash"
  },
  {
    "type": "seeed_lvgl_obj_delete",
    "message0": "删除 LVGL 对象 %1",
    "args0": [{ "type": "field_variable", "name": "VAR", "variable": "obj", "variableTypes": ["lv_obj_t"], "defaultType": "lv_obj_t" }],
    "previousStatement": null,
    "nextStatement": null,
    "colour": "#8BC34A",
    "tooltip": "删除 LVGL 对象",
    "icon": "fa-light fa-trash"
  },
  {
    "type": "seeed_lvgl_obj_set_event",
    "message0": "LVGL 对象 %1 事件 %2",
    "args0": [
      { "type": "field_variable", "name": "VAR", "variable": "obj", "variableTypes": ["lv_obj_t"], "defaultType": "lv_obj_t" },
      { "type": "field_dropdown", "name": "EVENT", "options": [["点击", "LV_EVENT_CLICKED"], ["值变化", "LV_EVENT_VALUE_CHANGED"], ["按下", "LV_EVENT_PRESSED"], ["释放", "LV_EVENT_RELEASED"], ["长按", "LV_EVENT_LONG_PRESSED"]] }
    ],
    "message1": "执行 %1",
    "args1": [{ "type": "input_statement", "name": "HANDLER" }],
    "previousStatement": null,
    "nextStatement": null,
    "colour": "#FFC107",
    "tooltip": "为对象注册事件回调",
    "icon": "fa-light fa-bolt"
  },
  {
    "type": "seeed_lvgl_label_create",
    "message0": "创建 %1 LVGL 标签 %2 父对象 %3",
    "args0": [
      { "type": "field_dropdown", "name": "SCOPE", "options": [["全局", "global"], ["局部", "local"]] },
      { "type": "field_input", "name": "VAR", "text": "label" },
      { "type": "field_variable", "name": "PARENT", "variable": "screen", "variableTypes": ["lv_obj_t"], "defaultType": "lv_obj_t" }
    ],
    "previousStatement": null,
    "nextStatement": null,
    "colour": "#2196F3",
    "tooltip": "创建 LVGL 标签控件",
    "icon": "fa-light fa-font"
  },
  {
    "type": "seeed_lvgl_label_set_text",
    "message0": "LVGL 标签 %1 设置文本 %2",
    "args0": [
      { "type": "field_variable", "name": "VAR", "variable": "label", "variableTypes": ["lv_obj_t"], "defaultType": "lv_obj_t" },
      { "type": "input_value", "name": "TEXT", "check": ["String"] }
    ],
    "previousStatement": null,
    "nextStatement": null,
    "colour": "#2196F3",
    "tooltip": "设置标签文本",
    "icon": "fa-light fa-font"
  },
  {
    "type": "seeed_lvgl_label_set_long_mode",
    "message0": "LVGL 标签 %1 长文本模式 %2",
    "args0": [
      { "type": "field_variable", "name": "VAR", "variable": "label", "variableTypes": ["lv_obj_t"], "defaultType": "lv_obj_t" },
      { "type": "field_dropdown", "name": "MODE", "options": [["自动扩展", "LV_LABEL_LONG_EXPAND"], ["换行", "LV_LABEL_LONG_BREAK"], ["省略号", "LV_LABEL_LONG_DOT"], ["滚动", "LV_LABEL_LONG_SROLL"], ["循环滚动", "LV_LABEL_LONG_SROLL_CIRC"], ["裁剪", "LV_LABEL_LONG_CROP"]] }
    ],
    "previousStatement": null,
    "nextStatement": null,
    "colour": "#2196F3",
    "tooltip": "设置标签长文本处理方式",
    "icon": "fa-light fa-text-width"
  },
  {
    "type": "seeed_lvgl_button_create",
    "message0": "创建 %1 LVGL 按钮 %2 父对象 %3",
    "args0": [
      { "type": "field_dropdown", "name": "SCOPE", "options": [["全局", "global"], ["局部", "local"]] },
      { "type": "field_input", "name": "VAR", "text": "btn" },
      { "type": "field_variable", "name": "PARENT", "variable": "screen", "variableTypes": ["lv_obj_t"], "defaultType": "lv_obj_t" }
    ],
    "previousStatement": null,
    "nextStatement": null,
    "colour": "#2196F3",
    "tooltip": "创建 LVGL 按钮控件",
    "icon": "fa-light fa-square-check"
  },
  {
    "type": "seeed_lvgl_slider_create",
    "message0": "创建 %1 LVGL 滑动条 %2 父对象 %3",
    "args0": [
      { "type": "field_dropdown", "name": "SCOPE", "options": [["全局", "global"], ["局部", "local"]] },
      { "type": "field_input", "name": "VAR", "text": "slider" },
      { "type": "field_variable", "name": "PARENT", "variable": "screen", "variableTypes": ["lv_obj_t"], "defaultType": "lv_obj_t" }
    ],
    "previousStatement": null,
    "nextStatement": null,
    "colour": "#FF9800",
    "tooltip": "创建 LVGL 滑动条",
    "icon": "fa-light fa-sliders"
  },
  {
    "type": "seeed_lvgl_slider_set_range",
    "message0": "LVGL 滑动条 %1 范围 最小 %2 最大 %3",
    "args0": [
      { "type": "field_variable", "name": "VAR", "variable": "slider", "variableTypes": ["lv_obj_t"], "defaultType": "lv_obj_t" },
      { "type": "input_value", "name": "MIN", "check": ["Number"] },
      { "type": "input_value", "name": "MAX", "check": ["Number"] }
    ],
    "previousStatement": null,
    "nextStatement": null,
    "colour": "#FF9800",
    "tooltip": "设置滑动条范围",
    "icon": "fa-light fa-sliders"
  },
  {
    "type": "seeed_lvgl_slider_set_value",
    "message0": "LVGL 滑动条 %1 设置值 %2 动画 %3",
    "args0": [
      { "type": "field_variable", "name": "VAR", "variable": "slider", "variableTypes": ["lv_obj_t"], "defaultType": "lv_obj_t" },
      { "type": "input_value", "name": "VALUE", "check": ["Number"] },
      { "type": "field_dropdown", "name": "ANIM", "options": [["开启", "LV_ANIM_ON"], ["关闭", "LV_ANIM_OFF"]] }
    ],
    "previousStatement": null,
    "nextStatement": null,
    "colour": "#FF9800",
    "tooltip": "设置滑动条当前值",
    "icon": "fa-light fa-sliders"
  },
  {
    "type": "seeed_lvgl_slider_get_value",
    "message0": "LVGL 滑动条 %1 的值",
    "args0": [{ "type": "field_variable", "name": "VAR", "variable": "slider", "variableTypes": ["lv_obj_t"], "defaultType": "lv_obj_t" }],
    "output": "Number",
    "colour": "#FF9800",
    "tooltip": "获取滑动条当前值",
    "icon": "fa-light fa-sliders"
  },
  {
    "type": "seeed_lvgl_bar_create",
    "message0": "创建 %1 LVGL 进度条 %2 父对象 %3",
    "args0": [
      { "type": "field_dropdown", "name": "SCOPE", "options": [["全局", "global"], ["局部", "local"]] },
      { "type": "field_input", "name": "VAR", "text": "bar" },
      { "type": "field_variable", "name": "PARENT", "variable": "screen", "variableTypes": ["lv_obj_t"], "defaultType": "lv_obj_t" }
    ],
    "previousStatement": null,
    "nextStatement": null,
    "colour": "#FF9800",
    "tooltip": "创建 LVGL 进度条",
    "icon": "fa-light fa-bars-progress"
  },
  {
    "type": "seeed_lvgl_bar_set_range",
    "message0": "LVGL 进度条 %1 范围 最小 %2 最大 %3",
    "args0": [
      { "type": "field_variable", "name": "VAR", "variable": "bar", "variableTypes": ["lv_obj_t"], "defaultType": "lv_obj_t" },
      { "type": "input_value", "name": "MIN", "check": ["Number"] },
      { "type": "input_value", "name": "MAX", "check": ["Number"] }
    ],
    "previousStatement": null,
    "nextStatement": null,
    "colour": "#FF9800",
    "tooltip": "设置进度条范围",
    "icon": "fa-light fa-bars-progress"
  },
  {
    "type": "seeed_lvgl_bar_set_value",
    "message0": "LVGL 进度条 %1 设置值 %2 动画 %3",
    "args0": [
      { "type": "field_variable", "name": "VAR", "variable": "bar", "variableTypes": ["lv_obj_t"], "defaultType": "lv_obj_t" },
      { "type": "input_value", "name": "VALUE", "check": ["Number"] },
      { "type": "field_dropdown", "name": "ANIM", "options": [["开启", "LV_ANIM_ON"], ["关闭", "LV_ANIM_OFF"]] }
    ],
    "previousStatement": null,
    "nextStatement": null,
    "colour": "#FF9800",
    "tooltip": "设置进度条当前值",
    "icon": "fa-light fa-bars-progress"
  },
  {
    "type": "seeed_lvgl_switch_create",
    "message0": "创建 %1 LVGL 开关 %2 父对象 %3",
    "args0": [
      { "type": "field_dropdown", "name": "SCOPE", "options": [["全局", "global"], ["局部", "local"]] },
      { "type": "field_input", "name": "VAR", "text": "sw" },
      { "type": "field_variable", "name": "PARENT", "variable": "screen", "variableTypes": ["lv_obj_t"], "defaultType": "lv_obj_t" }
    ],
    "previousStatement": null,
    "nextStatement": null,
    "colour": "#9C27B0",
    "tooltip": "创建 LVGL 开关",
    "icon": "fa-light fa-toggle-on"
  },
  {
    "type": "seeed_lvgl_switch_set",
    "message0": "LVGL 开关 %1 设置 %2 动画 %3",
    "args0": [
      { "type": "field_variable", "name": "VAR", "variable": "sw", "variableTypes": ["lv_obj_t"], "defaultType": "lv_obj_t" },
      { "type": "field_dropdown", "name": "STATE", "options": [["开启", "ON"], ["关闭", "OFF"], ["切换", "TOGGLE"]] },
      { "type": "field_dropdown", "name": "ANIM", "options": [["开启", "LV_ANIM_ON"], ["关闭", "LV_ANIM_OFF"]] }
    ],
    "previousStatement": null,
    "nextStatement": null,
    "colour": "#9C27B0",
    "tooltip": "设置或切换开关状态",
    "icon": "fa-light fa-toggle-on"
  },
  {
    "type": "seeed_lvgl_switch_get_state",
    "message0": "LVGL 开关 %1 是否开启",
    "args0": [{ "type": "field_variable", "name": "VAR", "variable": "sw", "variableTypes": ["lv_obj_t"], "defaultType": "lv_obj_t" }],
    "output": "Boolean",
    "colour": "#9C27B0",
    "tooltip": "读取开关状态",
    "icon": "fa-light fa-toggle-on"
  },
  {
    "type": "seeed_lvgl_checkbox_create",
    "message0": "创建 %1 LVGL 复选框 %2 父对象 %3 文本 %4",
    "args0": [
      { "type": "field_dropdown", "name": "SCOPE", "options": [["全局", "global"], ["局部", "local"]] },
      { "type": "field_input", "name": "VAR", "text": "checkbox" },
      { "type": "field_variable", "name": "PARENT", "variable": "screen", "variableTypes": ["lv_obj_t"], "defaultType": "lv_obj_t" },
      { "type": "input_value", "name": "TEXT", "check": ["String"] }
    ],
    "previousStatement": null,
    "nextStatement": null,
    "colour": "#9C27B0",
    "tooltip": "创建 LVGL 复选框",
    "icon": "fa-light fa-square-check"
  },
  {
    "type": "seeed_lvgl_image_create",
    "message0": "创建 %1 LVGL 图像 %2 父对象 %3",
    "args0": [
      { "type": "field_dropdown", "name": "SCOPE", "options": [["全局", "global"], ["局部", "local"]] },
      { "type": "field_input", "name": "VAR", "text": "img" },
      { "type": "field_variable", "name": "PARENT", "variable": "screen", "variableTypes": ["lv_obj_t"], "defaultType": "lv_obj_t" }
    ],
    "previousStatement": null,
    "nextStatement": null,
    "colour": "#2196F3",
    "tooltip": "创建 LVGL 图像控件",
    "icon": "fa-light fa-image"
  },
  {
    "type": "seeed_lvgl_image_set_src",
    "message0": "LVGL 图像 %1 设置源 %2",
    "args0": [
      { "type": "field_variable", "name": "VAR", "variable": "img", "variableTypes": ["lv_obj_t"], "defaultType": "lv_obj_t" },
      { "type": "input_value", "name": "SRC" }
    ],
    "previousStatement": null,
    "nextStatement": null,
    "colour": "#2196F3",
    "tooltip": "设置图片文件路径、符号或图片数组",
    "icon": "fa-light fa-image"
  },
  {
    "type": "seeed_lvgl_image_set_transform",
    "message0": "LVGL 图像 %1 缩放 %2 角度0.1度 %3",
    "args0": [
      { "type": "field_variable", "name": "VAR", "variable": "img", "variableTypes": ["lv_obj_t"], "defaultType": "lv_obj_t" },
      { "type": "input_value", "name": "ZOOM", "check": ["Number"] },
      { "type": "input_value", "name": "ANGLE", "check": ["Number"] }
    ],
    "previousStatement": null,
    "nextStatement": null,
    "colour": "#2196F3",
    "tooltip": "设置图像缩放和旋转角度",
    "icon": "fa-light fa-image"
  },
  {
    "type": "seeed_lvgl_style_color",
    "message0": "LVGL 对象 %1 颜色样式 部件 %2 状态 %3 属性 %4 颜色 %5",
    "args0": [
      { "type": "field_variable", "name": "VAR", "variable": "obj", "variableTypes": ["lv_obj_t"], "defaultType": "lv_obj_t" },
      { "type": "field_dropdown", "name": "PART", "options": [["主部件", "LV_OBJ_PART_MAIN"], ["按钮主部件", "LV_BTN_PART_MAIN"], ["滑动条背景", "LV_SLIDER_PART_BG"], ["滑动条指示", "LV_SLIDER_PART_INDIC"], ["滑动条旋钮", "LV_SLIDER_PART_KNOB"]] },
      { "type": "field_dropdown", "name": "STATE", "options": [["默认", "LV_STATE_DEFAULT"], ["按下", "LV_STATE_PRESSED"], ["选中", "LV_STATE_CHECKED"], ["禁用", "LV_STATE_DISABLED"]] },
      { "type": "field_dropdown", "name": "PROPERTY", "options": [["背景色", "bg_color"], ["边框色", "border_color"], ["文字色", "text_color"], ["线条色", "line_color"]] },
      { "type": "input_value", "name": "COLOR" }
    ],
    "previousStatement": null,
    "nextStatement": null,
    "colour": "#FFC107",
    "tooltip": "设置 LVGL v7 本地颜色样式",
    "icon": "fa-light fa-palette"
  },
  {
    "type": "seeed_lvgl_style_number",
    "message0": "LVGL 对象 %1 数值样式 部件 %2 状态 %3 属性 %4 值 %5",
    "args0": [
      { "type": "field_variable", "name": "VAR", "variable": "obj", "variableTypes": ["lv_obj_t"], "defaultType": "lv_obj_t" },
      { "type": "field_dropdown", "name": "PART", "options": [["主部件", "LV_OBJ_PART_MAIN"], ["按钮主部件", "LV_BTN_PART_MAIN"], ["滑动条背景", "LV_SLIDER_PART_BG"], ["滑动条指示", "LV_SLIDER_PART_INDIC"], ["滑动条旋钮", "LV_SLIDER_PART_KNOB"]] },
      { "type": "field_dropdown", "name": "STATE", "options": [["默认", "LV_STATE_DEFAULT"], ["按下", "LV_STATE_PRESSED"], ["选中", "LV_STATE_CHECKED"], ["禁用", "LV_STATE_DISABLED"]] },
      { "type": "field_dropdown", "name": "PROPERTY", "options": [["圆角", "radius"], ["边框宽", "border_width"], ["背景不透明度", "bg_opa"], ["文字不透明度", "text_opa"], ["内边距", "pad_inner"], ["线宽", "line_width"]] },
      { "type": "input_value", "name": "VALUE", "check": ["Number"] }
    ],
    "previousStatement": null,
    "nextStatement": null,
    "colour": "#FFC107",
    "tooltip": "设置 LVGL v7 本地数值样式",
    "icon": "fa-light fa-sliders"
  },
  {
    "type": "seeed_lvgl_color",
    "message0": "LVGL 颜色 %1",
    "args0": [
      { "type": "field_dropdown", "name": "COLOR", "options": [["白色", "LV_COLOR_WHITE"], ["黑色", "LV_COLOR_BLACK"], ["红色", "LV_COLOR_RED"], ["绿色", "LV_COLOR_GREEN"], ["蓝色", "LV_COLOR_BLUE"], ["黄色", "LV_COLOR_YELLOW"], ["青色", "LV_COLOR_CYAN"], ["紫色", "LV_COLOR_PURPLE"], ["灰色", "LV_COLOR_GRAY"], ["银色", "LV_COLOR_SILVER"]] }
    ],
    "output": "lv_color_t",
    "colour": "#FFC107",
    "tooltip": "LVGL 预设颜色",
    "icon": "fa-light fa-palette"
  },
  {
    "type": "seeed_lvgl_color_rgb",
    "message0": "LVGL RGB 颜色 %1",
    "args0": [{ "type": "field_colour_hsv_sliders", "name": "COLOR", "colour": "#ffffff" }],
    "output": "lv_color_t",
    "colour": "#FFC107",
    "tooltip": "生成 lv_color_make(r,g,b)",
    "icon": "fa-light fa-eye-dropper"
  }
]
