{
  "kind": "category",
  "name": "CAN-Bus",
  "colour": "#5C81A6",
  "contents": [
    { "kind": "block", "type": "canbus_init" },
    { "kind": "block", "type": "canbus_is_ready" },
    { "kind": "block", "type": "canbus_send_test" },
    { "kind": "block", "type": "canbus_read_message" },
    { "kind": "block", "type": "canbus_last_id" },
    { "kind": "block", "type": "canbus_last_length" },
    { "kind": "block", "type": "canbus_data_byte" },
    { "kind": "block", "type": "canbus_obd_request" },
    { "kind": "block", "type": "canbus_send_message", "inputs": { "ID": { "shadow": { "type": "math_number", "fields": { "NUM": 2015 } } }, "D0": { "shadow": { "type": "math_number", "fields": { "NUM": 2 } } }, "D1": { "shadow": { "type": "math_number", "fields": { "NUM": 1 } } }, "D2": { "shadow": { "type": "math_number", "fields": { "NUM": 12 } } }, "D3": { "shadow": { "type": "math_number", "fields": { "NUM": 0 } } }, "D4": { "shadow": { "type": "math_number", "fields": { "NUM": 0 } } }, "D5": { "shadow": { "type": "math_number", "fields": { "NUM": 0 } } }, "D6": { "shadow": { "type": "math_number", "fields": { "NUM": 0 } } }, "D7": { "shadow": { "type": "math_number", "fields": { "NUM": 0 } } } } }
  ]
}