{
  "kind": "category",
  "name": "STM32步进电机控制快捷模块",
  "icon": "iconfont icon-motor",
  "colour": "#FF6B35",
  "contents": [
    {
      "kind": "label",
      "text": "初始化"
    },
    {
      "kind": "block",
      "type": "stepper_ctrl_init",
      "inputs": {
        "SPEED": {
          "shadow": {
            "type": "math_number",
            "fields": {
              "NUM": "1000"
            }
          }
        }
      }
    },
    {
      "kind": "label",
      "text": "控制"
    },
    {
      "kind": "block",
      "type": "stepper_ctrl_start",
      "inputs": {
        "TARGET": {
          "shadow": {
            "type": "math_number",
            "fields": {
              "NUM": "800"
            }
          }
        }
      }
    },
    {
      "kind": "block",
      "type": "stepper_ctrl_stop"
    },
    {
      "kind": "block",
      "type": "stepper_ctrl_set_speed",
      "inputs": {
        "SPEED": {
          "shadow": {
            "type": "math_number",
            "fields": {
              "NUM": "1000"
            }
          }
        }
      }
    },
    {
      "kind": "block",
      "type": "stepper_ctrl_set_rpm",
      "inputs": {
        "RPM": {
          "shadow": {
            "type": "math_number",
            "fields": {
              "NUM": "60"
            }
          }
        },
        "SPR": {
          "shadow": {
            "type": "math_number",
            "fields": {
              "NUM": "200"
            }
          }
        }
      }
    },
    {
      "kind": "block",
      "type": "stepper_ctrl_set_direction"
    },
    {
      "kind": "label",
      "text": "状态"
    },
    {
      "kind": "block",
      "type": "stepper_ctrl_tick"
    },
    {
      "kind": "block",
      "type": "stepper_ctrl_is_running"
    },
    {
      "kind": "block",
      "type": "stepper_ctrl_get_steps"
    },
    {
      "kind": "block",
      "type": "stepper_ctrl_reset_steps"
    },
    {
      "kind": "block",
      "type": "stepper_ctrl_is_front_limit"
    },
    {
      "kind": "block",
      "type": "stepper_ctrl_is_back_limit"
    },
    {
      "kind": "label",
      "text": "事件"
    },
    {
      "kind": "block",
      "type": "stepper_ctrl_on_target_done"
    },
    {
      "kind": "block",
      "type": "stepper_ctrl_on_front_limit"
    },
    {
      "kind": "block",
      "type": "stepper_ctrl_on_back_limit"
    }
  ]
}
