{
  "kind": "category",
  "name": "RPC WiFiManager",
  "icon": "fa-light fa-router",
  "colour": "#2E7D32",
  "contents": [
    {
      "kind": "category",
      "name": "对象与连接",
      "icon": "fa-light fa-router",
      "colour": "#2E7D32",
      "contents": [
        {
          "kind": "block",
          "type": "seeed_rpcwifimanager_create"
        },
        {
          "kind": "block",
          "type": "seeed_rpcwifimanager_auto_connect",
          "inputs": {
            "AP_NAME": {
              "shadow": {
                "type": "text",
                "fields": {
                  "TEXT": "WioConfig"
                }
              }
            },
            "AP_PASSWORD": {
              "shadow": {
                "type": "text",
                "fields": {
                  "TEXT": "12345678"
                }
              }
            }
          }
        },
        {
          "kind": "block",
          "type": "seeed_rpcwifimanager_auto_connect_default"
        },
        {
          "kind": "block",
          "type": "seeed_rpcwifimanager_start_portal",
          "inputs": {
            "AP_NAME": {
              "shadow": {
                "type": "text",
                "fields": {
                  "TEXT": "WioConfig"
                }
              }
            },
            "AP_PASSWORD": {
              "shadow": {
                "type": "text",
                "fields": {
                  "TEXT": "12345678"
                }
              }
            }
          }
        },
        {
          "kind": "block",
          "type": "seeed_rpcwifimanager_start_portal_default"
        },
        {
          "kind": "block",
          "type": "seeed_rpcwifimanager_reset_settings"
        }
      ]
    },
    {
      "kind": "category",
      "name": "门户设置",
      "icon": "fa-light fa-sliders",
      "colour": "#558B2F",
      "contents": [
        {
          "kind": "block",
          "type": "seeed_rpcwifimanager_set_portal_timeout",
          "inputs": {
            "SECONDS": {
              "shadow": {
                "type": "math_number",
                "fields": {
                  "NUM": 180
                }
              }
            }
          }
        },
        {
          "kind": "block",
          "type": "seeed_rpcwifimanager_set_connect_timeout",
          "inputs": {
            "SECONDS": {
              "shadow": {
                "type": "math_number",
                "fields": {
                  "NUM": 30
                }
              }
            }
          }
        },
        {
          "kind": "block",
          "type": "seeed_rpcwifimanager_set_debug_output"
        },
        {
          "kind": "block",
          "type": "seeed_rpcwifimanager_set_min_quality",
          "inputs": {
            "QUALITY": {
              "shadow": {
                "type": "math_number",
                "fields": {
                  "NUM": 8
                }
              }
            }
          }
        },
        {
          "kind": "block",
          "type": "seeed_rpcwifimanager_set_remove_duplicate_aps"
        },
        {
          "kind": "block",
          "type": "seeed_rpcwifimanager_set_break_after_save"
        },
        {
          "kind": "block",
          "type": "seeed_rpcwifimanager_set_ap_static_ip",
          "inputs": {
            "IP": {
              "shadow": {
                "type": "text",
                "fields": {
                  "TEXT": "192.168.4.1"
                }
              }
            },
            "GATEWAY": {
              "shadow": {
                "type": "text",
                "fields": {
                  "TEXT": "192.168.4.1"
                }
              }
            },
            "SUBNET": {
              "shadow": {
                "type": "text",
                "fields": {
                  "TEXT": "255.255.255.0"
                }
              }
            }
          }
        },
        {
          "kind": "block",
          "type": "seeed_rpcwifimanager_set_sta_static_ip",
          "inputs": {
            "IP": {
              "shadow": {
                "type": "text",
                "fields": {
                  "TEXT": "192.168.1.80"
                }
              }
            },
            "GATEWAY": {
              "shadow": {
                "type": "text",
                "fields": {
                  "TEXT": "192.168.1.1"
                }
              }
            },
            "SUBNET": {
              "shadow": {
                "type": "text",
                "fields": {
                  "TEXT": "255.255.255.0"
                }
              }
            }
          }
        },
        {
          "kind": "block",
          "type": "seeed_rpcwifimanager_set_custom_head"
        }
      ]
    },
    {
      "kind": "category",
      "name": "状态读取",
      "icon": "fa-light fa-circle-info",
      "colour": "#1565C0",
      "contents": [
        {
          "kind": "block",
          "type": "seeed_rpcwifimanager_get_portal_ssid"
        },
        {
          "kind": "block",
          "type": "seeed_rpcwifimanager_get_ssid"
        },
        {
          "kind": "block",
          "type": "seeed_rpcwifimanager_get_password"
        }
      ]
    },
    {
      "kind": "category",
      "name": "自定义参数",
      "icon": "fa-light fa-sliders",
      "colour": "#00838F",
      "contents": [
        {
          "kind": "block",
          "type": "seeed_rpcwifimanager_parameter_create"
        },
        {
          "kind": "block",
          "type": "seeed_rpcwifimanager_parameter_create_html"
        },
        {
          "kind": "block",
          "type": "seeed_rpcwifimanager_add_parameter"
        },
        {
          "kind": "block",
          "type": "seeed_rpcwifimanager_parameter_value"
        },
        {
          "kind": "block",
          "type": "seeed_rpcwifimanager_parameter_id"
        },
        {
          "kind": "block",
          "type": "seeed_rpcwifimanager_parameter_placeholder"
        },
        {
          "kind": "block",
          "type": "seeed_rpcwifimanager_parameter_length"
        }
      ]
    },
    {
      "kind": "category",
      "name": "回调",
      "icon": "fa-light fa-bell",
      "colour": "#7B1FA2",
      "contents": [
        {
          "kind": "block",
          "type": "seeed_rpcwifimanager_on_portal_start"
        },
        {
          "kind": "block",
          "type": "seeed_rpcwifimanager_on_save_success"
        }
      ]
    }
  ]
}
