{
  "kind": "category",
  "name": "CST816S触摸屏",
  "name_en": "CST816S Touch Screen",
  "icon": "fa-solid fa-hand-pointer",
  "colour": "#FF6B6B",
  "contents": [
    {
      "kind": "label",
      "text": "初始化"
    },
    {
      "kind": "block",
      "type": "cst816s_init",
      "inputs": {
        "RST": {"shadow": {"type": "math_number", "fields": {"NUM": "4"}}},
        "IRQ": {"shadow": {"type": "math_number", "fields": {"NUM": "5"}}}
      }
    },
    {
      "kind": "label",
      "text": "读取数据"
    },
    {
      "kind": "block",
      "type": "cst816s_read_gesture"
    },
    {
      "kind": "block",
      "type": "cst816s_read_position"
    },
    {
      "kind": "block",
      "type": "cst816s_is_available"
    },
    {
      "kind": "label",
      "text": "配置"
    },
    {
      "kind": "block",
      "type": "cst816s_enable_double_click"
    },
    {
      "kind": "block",
      "type": "cst816s_enable_auto_sleep"
    },
    {
      "kind": "block",
      "type": "cst816s_disable_auto_sleep"
    },
    {
      "kind": "block",
      "type": "cst816s_sleep"
    }
  ]
}
