{
  "kind": "category",
  "name": "遥控手柄",
  "icon": "fa-light fa-gamepad",
  "colour": "#5B80A5",
  "contents": [
    {
      "kind": "label",
      "text": "手柄初始化"
    },
    {
      "kind": "block",
      "type": "emakefun_gamepad_initialize"
    },
    {
      "kind": "block",
      "type": "emakefun_gamepad_model_create"
    },
    {
      "kind": "block",
      "type": "emakefun_gamepad_attach_model"
    },
    {
      "kind": "label",
      "text": "按键事件"
    },
    {
      "kind": "block",
      "type": "emakefun_gamepad_button_pressed"
    },
    {
      "kind": "block",
      "type": "emakefun_gamepad_button_released"
    },
    {
      "kind": "block",
      "type": "emakefun_gamepad_get_button_state"
    },
    {
      "kind": "label",
      "text": "摇杆与传感器"
    },
    {
      "kind": "block",
      "type": "emakefun_gamepad_get_joystick_x"
    },
    {
      "kind": "block",
      "type": "emakefun_gamepad_get_joystick_y"
    },
    {
      "kind": "block",
      "type": "emakefun_gamepad_new_joystick_coordinate"
    },
    {
      "kind": "block",
      "type": "emakefun_gamepad_get_gravity_x"
    },
    {
      "kind": "block",
      "type": "emakefun_gamepad_get_gravity_y"
    },
    {
      "kind": "block",
      "type": "emakefun_gamepad_get_gravity_z"
    },
    {
      "kind": "block",
      "type": "emakefun_gamepad_new_gravity_acceleration"
    },
    {
      "kind": "label",
      "text": "2.4G无线通信"
    },
    {
      "kind": "block",
      "type": "emakefun_gamepad_publisher_rf24_create",
      "inputs": {
        "CE_PIN": {
          "shadow": {
            "type": "math_number",
            "fields": {
              "NUM": 7
            }
          }
        },
        "CS_PIN": {
          "shadow": {
            "type": "math_number",
            "fields": {
              "NUM": 8
            }
          }
        },
        "CHANNEL": {
          "shadow": {
            "type": "math_number",
            "fields": {
              "NUM": 115
            }
          }
        },
        "ADDR_WIDTH": {
          "shadow": {
            "type": "math_number",
            "fields": {
              "NUM": 5
            }
          }
        },
        "ADDRESS": {
          "shadow": {
            "type": "math_number",
            "fields": {
              "NUM": 73014444097
            }
          }
        }
      }
    },
    {
      "kind": "block",
      "type": "emakefun_gamepad_model_add_observer"
    },
    {
      "kind": "block",
      "type": "emakefun_gamepad_subscriber_rf24_create",
      "inputs": {
        "CE_PIN": {
          "shadow": {
            "type": "math_number",
            "fields": {
              "NUM": 7
            }
          }
        },
        "CS_PIN": {
          "shadow": {
            "type": "math_number",
            "fields": {
              "NUM": 8
            }
          }
        },
        "CHANNEL": {
          "shadow": {
            "type": "math_number",
            "fields": {
              "NUM": 115
            }
          }
        },
        "ADDR_WIDTH": {
          "shadow": {
            "type": "math_number",
            "fields": {
              "NUM": 5
            }
          }
        },
        "ADDRESS": {
          "shadow": {
            "type": "math_number",
            "fields": {
              "NUM": 73014444097
            }
          }
        }
      }
    },
    {
      "kind": "block",
      "type": "emakefun_gamepad_subscriber_rf24_attach_model"
    },
    {
      "kind": "label",
      "text": "BLE蓝牙通信"
    },
    {
      "kind": "block",
      "type": "emakefun_gamepad_publisher_ble_create"
    },
    {
      "kind": "block",
      "type": "emakefun_gamepad_subscriber_ble_create"
    },
    {
      "kind": "block",
      "type": "emakefun_gamepad_subscriber_ble_attach_model"
    }
  ]
}